pinnflow/__init__.py
pinnflow/source.py
pinnflow-1.0.7.dist-info/licenses/LICENSE
pinnflow-1.0.7.dist-info/METADATA
pinnflow-1.0.7.dist-info/WHEEL
pinnflow-1.0.7.dist-info/top_level.txt
pinnflow-1.0.7.dist-info/RECORD
