Metadata-Version: 2.4
Name: pinnflow
Version: 1.0.7
Author-email: Naomi Shakespeare-Rees <eenmsr@leeds.ac.uk>
Classifier: Programming Language :: Python :: 3
Classifier: License :: OSI Approved :: MIT License
Classifier: Operating System :: OS Independent
Requires-Python: >=3.10
License-File: LICENSE
Requires-Dist: numpy
Requires-Dist: chaosmagpy
Requires-Dist: torch
Requires-Dist: matplotlib
Requires-Dist: cartopy
Requires-Dist: scikit-learn
Provides-Extra: test
Requires-Dist: pytest==6.2.5; extra == "test"
Dynamic: license-file
